[
  {
    "Trustee": "LOGS.COM",
    "Sale_date": "5/29/26",
    "Sale_time": "10:00 AM",
    "FileNo": "26-041484",
    "PropAddress": "3131 Jennifer Lane",
    "PropCity": "Country Club",
    "PropZip": "",
    "County": "Andrew",
    "OpeningBid": "$183,229",
    "vendor": "Auction.com",
    "status- DROP DOWN": "Cancelled",
    "Foreclosure Status": "On Hold"
  },
  {
    "Trustee": "LOGS.COM",
    "Sale_date": "6/9/26",
    "Sale_time": "12:30 PM",
    "FileNo": "26-041605",
    "PropAddress": "909 Kent Road",
    "PropCity": "Mexico",
    "PropZip": "",
    "County": "Audrain",
    "OpeningBid": "",
    "vendor": "Auction.com",
    "status- DROP DOWN": "",
    "Foreclosure Status": ""
  },
  {
    "Trustee": "LOGS.COM",
    "Sale_date": "6/16/26",
    "Sale_time": "12:30 PM",
    "FileNo": "25-040152",
    "PropAddress": "213 East Woodlawn Street",
    "PropCity": "Vandalia",
    "PropZip": "",
    "County": "Audrain",
    "OpeningBid": "",
    "vendor": "Auction.com",
    "status- DROP DOWN": "",
    "Foreclosure Status": ""
  },
  {
    "Trustee": "LOGS.COM",
    "Sale_date": "6/18/26",
    "Sale_time": "12:00 PM",
    "FileNo": "26-041798",
    "PropAddress": "1175 East Calvin Drive",
    "PropCity": "Hartsburg",
    "PropZip": "",
    "County": "Boone",
    "OpeningBid": "",
    "vendor": "Auction.com",
    "status- DROP DOWN": "",
    "Foreclosure Status": ""
  },
  {
    "Trustee": "LOGS.COM",
    "Sale_date": "6/4/26",
    "Sale_time": "12:00 PM",
    "FileNo": "13-022567",
    "PropAddress": "406 Kentucky St",
    "PropCity": "Saint Joseph",
    "PropZip": "",
    "County": "Buchanan",
    "OpeningBid": "",
    "vendor": "Auction.com",
    "status- DROP DOWN": "",
    "Foreclosure Status": ""
  },
  {
    "Trustee": "LOGS.COM",
    "Sale_date": "6/4/26",
    "Sale_time": "10:00 AM",
    "FileNo": "25-041244",
    "PropAddress": "262 Leisure Lane",
    "PropCity": "Montreal",
    "PropZip": "",
    "County": "Camden",
    "OpeningBid": "",
    "vendor": "Auction.com",
    "status- DROP DOWN": "",
    "Foreclosure Status": ""
  },
  {
    "Trustee": "LOGS.COM",
    "Sale_date": "6/11/26",
    "Sale_time": "11:00 AM",
    "FileNo": "26-041858",
    "PropAddress": "2019 Woodlawn Avenue",
    "PropCity": "Cape Girardeau",
    "PropZip": "",
    "County": "Cape Girardeau",
    "OpeningBid": "",
    "vendor": "Auction.com",
    "status- DROP DOWN": "",
    "Foreclosure Status": ""
  },
  {
    "Trustee": "LOGS.COM",
    "Sale_date": "6/9/26",
    "Sale_time": "10:00 AM",
    "FileNo": "26-041480",
    "PropAddress": "22104 Crystal Avenue",
    "PropCity": "Peculiar",
    "PropZip": "",
    "County": "Cass",
    "OpeningBid": "",
    "vendor": "Auction.com",
    "status- DROP DOWN": "Cancelled",
    "Foreclosure Status": "On Hold"
  },
  {
    "Trustee": "LOGS.COM",
    "Sale_date": "5/26/26",
    "Sale_time": "10:00 AM",
    "FileNo": "26-041702",
    "PropAddress": "520 Thornton Street",
    "PropCity": "Liberty",
    "PropZip": "",
    "County": "Clay",
    "OpeningBid": "$88,630.68",
    "vendor": "Auction.com",
    "status- DROP DOWN": "",
    "Foreclosure Status": ""
  },
  {
    "Trustee": "LOGS.COM",
    "Sale_date": "6/9/26",
    "Sale_time": "09:30 AM",
    "FileNo": "25-041083",
    "PropAddress": "5001 Northeast 56th Terrace",
    "PropCity": "Kansas City",
    "PropZip": "",
    "County": "Clay",
    "OpeningBid": "",
    "vendor": "Ascribe",
    "status- DROP DOWN": "",
    "Foreclosure Status": ""
  },
  {
    "Trustee": "LOGS.COM",
    "Sale_date": "6/16/26",
    "Sale_time": "09:30 AM",
    "FileNo": "26-041595",
    "PropAddress": "5536 Northeast 58th Street",
    "PropCity": "Kansas City",
    "PropZip": "",
    "County": "Clay",
    "OpeningBid": "",
    "vendor": "Servicelink/Hudson Marshall",
    "status- DROP DOWN": "",
    "Foreclosure Status": ""
  },
  {
    "Trustee": "LOGS.COM",
    "Sale_date": "6/2/26",
    "Sale_time": "10:00 AM",
    "FileNo": "26-041721",
    "PropAddress": "455 Grant Street",
    "PropCity": "Saint Clair",
    "PropZip": "",
    "County": "Franklin",
    "OpeningBid": "",
    "vendor": "Auction.com",
    "status- DROP DOWN": "",
    "Foreclosure Status": ""
  },
  {
    "Trustee": "LOGS.COM",
    "Sale_date": "6/5/26",
    "Sale_time": "11:00 AM",
    "FileNo": "26-041733",
    "PropAddress": "1500 Highway K",
    "PropCity": "Saint Clair",
    "PropZip": "",
    "County": "Franklin",
    "OpeningBid": "",
    "vendor": "",
    "status- DROP DOWN": "",
    "Foreclosure Status": ""
  },
  {
    "Trustee": "LOGS.COM",
    "Sale_date": "6/16/26",
    "Sale_time": "10:00 AM",
    "FileNo": "26-041839",
    "PropAddress": "45 Durham Drive",
    "PropCity": "Washington",
    "PropZip": "",
    "County": "Franklin",
    "OpeningBid": "",
    "vendor": "Auction.com",
    "status- DROP DOWN": "",
    "Foreclosure Status": ""
  },
  {
    "Trustee": "LOGS.COM",
    "Sale_date": "6/16/26",
    "Sale_time": "12:00 PM",
    "FileNo": "25-040983",
    "PropAddress": "502 South Cuba Street",
    "PropCity": "Owensville",
    "PropZip": "",
    "County": "Gasconade",
    "OpeningBid": "",
    "vendor": "ServiceLink",
    "status- DROP DOWN": "",
    "Foreclosure Status": ""
  },
  {
    "Trustee": "LOGS.COM",
    "Sale_date": "5/27/26",
    "Sale_time": "10:00 AM",
    "FileNo": "26-041760",
    "PropAddress": "1604 North Rogers Street",
    "PropCity": "Independence",
    "PropZip": "",
    "County": "Jackson",
    "OpeningBid": "",
    "vendor": "Auction.com",
    "status- DROP DOWN": "Postponed",
    "Foreclosure Status": ""
  },
  {
    "Trustee": "LOGS.COM",
    "Sale_date": "5/27/26",
    "Sale_time": "11:00 AM",
    "FileNo": "23-038826",
    "PropAddress": "822 NE Orchard Drive",
    "PropCity": "Lees Summit",
    "PropZip": "",
    "County": "Jackson",
    "OpeningBid": "$171,945.14",
    "vendor": "",
    "status- DROP DOWN": "",
    "Foreclosure Status": ""
  },
  {
    "Trustee": "LOGS.COM",
    "Sale_date": "5/27/26",
    "Sale_time": "11:00 AM",
    "FileNo": "26-041663",
    "PropAddress": "1209 Southwest Madison Street",
    "PropCity": "Lees Summit",
    "PropZip": "",
    "County": "Jackson",
    "OpeningBid": "$174,800",
    "vendor": "Servicelink/Hudson Marshall",
    "status- DROP DOWN": "",
    "Foreclosure Status": ""
  },
  {
    "Trustee": "LOGS.COM",
    "Sale_date": "5/27/26",
    "Sale_time": "11:00 AM",
    "FileNo": "26-041672",
    "PropAddress": "2223 South Evanston Avenue",
    "PropCity": "Independence",
    "PropZip": "",
    "County": "Jackson",
    "OpeningBid": "",
    "vendor": "",
    "status- DROP DOWN": "",
    "Foreclosure Status": ""
  },
  {
    "Trustee": "LOGS.COM",
    "Sale_date": "6/10/26",
    "Sale_time": "10:00 AM",
    "FileNo": "25-041378",
    "PropAddress": "2942 East 29th Street",
    "PropCity": "Kansas City",
    "PropZip": "",
    "County": "Jackson",
    "OpeningBid": "",
    "vendor": "Servicelink/Hudson Marshall",
    "status- DROP DOWN": "",
    "Foreclosure Status": ""
  },
  {
    "Trustee": "LOGS.COM",
    "Sale_date": "6/17/26",
    "Sale_time": "10:00 AM",
    "FileNo": "26-041513",
    "PropAddress": "8107 Ward Pkwy",
    "PropCity": "Kansas City",
    "PropZip": "",
    "County": "Jackson",
    "OpeningBid": "",
    "vendor": "Servicelink/Hudson Marshall",
    "status- DROP DOWN": "",
    "Foreclosure Status": ""
  },
  {
    "Trustee": "LOGS.COM",
    "Sale_date": "6/17/26",
    "Sale_time": "11:00 AM",
    "FileNo": "26-041563",
    "PropAddress": "2521 South Ellison Way",
    "PropCity": "Independence",
    "PropZip": "",
    "County": "Jackson",
    "OpeningBid": "",
    "vendor": "Servicelink/Hudson Marshall",
    "status- DROP DOWN": "",
    "Foreclosure Status": ""
  },
  {
    "Trustee": "LOGS.COM",
    "Sale_date": "6/2/26",
    "Sale_time": "10:00 AM",
    "FileNo": "26-041533",
    "PropAddress": "610 Webb Street",
    "PropCity": "Duenweg",
    "PropZip": "",
    "County": "Jasper",
    "OpeningBid": "$111,000",
    "vendor": "Auction.com",
    "status- DROP DOWN": "",
    "Foreclosure Status": ""
  },
  {
    "Trustee": "LOGS.COM",
    "Sale_date": "6/23/26",
    "Sale_time": "10:30 AM",
    "FileNo": "26-041836",
    "PropAddress": "102 Golf Road",
    "PropCity": "Webb City",
    "PropZip": "",
    "County": "Jasper",
    "OpeningBid": "",
    "vendor": "Ascribe",
    "status- DROP DOWN": "Cancelled",
    "Foreclosure Status": "On Hold"
  },
  {
    "Trustee": "LOGS.COM",
    "Sale_date": "5/28/26",
    "Sale_time": "09:15 AM",
    "FileNo": "26-041472",
    "PropAddress": "14 Pleasant Valley Terrace",
    "PropCity": "Arnold",
    "PropZip": "",
    "County": "Jefferson",
    "OpeningBid": "$60,450",
    "vendor": "Xome",
    "status- DROP DOWN": "",
    "Foreclosure Status": ""
  },
  {
    "Trustee": "LOGS.COM",
    "Sale_date": "6/18/26",
    "Sale_time": "09:15 AM",
    "FileNo": "25-041370",
    "PropAddress": "1812 Future Street",
    "PropCity": "De Soto",
    "PropZip": "",
    "County": "Jefferson",
    "OpeningBid": "",
    "vendor": "Servicelink/Hudson Marshall",
    "status- DROP DOWN": "",
    "Foreclosure Status": ""
  },
  {
    "Trustee": "LOGS.COM",
    "Sale_date": "6/1/26",
    "Sale_time": "10:30 AM",
    "FileNo": "26-041548",
    "PropAddress": "424 Apple Lane",
    "PropCity": "Goodman",
    "PropZip": "",
    "County": "McDonald",
    "OpeningBid": "$121,225",
    "vendor": "Servicelink/Hudson Marshall",
    "status- DROP DOWN": "",
    "Foreclosure Status": ""
  },
  {
    "Trustee": "LOGS.COM",
    "Sale_date": "6/9/26",
    "Sale_time": "09:30 AM",
    "FileNo": "26-041606",
    "PropAddress": "12115 Hammer Road",
    "PropCity": "Neosho",
    "PropZip": "",
    "County": "Newton",
    "OpeningBid": "",
    "vendor": "ServiceLink",
    "status- DROP DOWN": "",
    "Foreclosure Status": ""
  },
  {
    "Trustee": "LOGS.COM",
    "Sale_date": "6/4/26",
    "Sale_time": "11:30 AM",
    "FileNo": "26-041596",
    "PropAddress": "220 Harlin Drive",
    "PropCity": "Gainesville",
    "PropZip": "",
    "County": "Ozark",
    "OpeningBid": "$94,250",
    "vendor": "Servicelink/Hudson Marshall",
    "status- DROP DOWN": "",
    "Foreclosure Status": ""
  },
  {
    "Trustee": "LOGS.COM",
    "Sale_date": "6/2/26",
    "Sale_time": "11:30 AM",
    "FileNo": "26-041722",
    "PropAddress": "1101 North Main Street",
    "PropCity": "Perryville",
    "PropZip": "",
    "County": "Perry",
    "OpeningBid": "",
    "vendor": "ServiceLink",
    "status- DROP DOWN": "",
    "Foreclosure Status": ""
  },
  {
    "Trustee": "LOGS.COM",
    "Sale_date": "5/26/26",
    "Sale_time": "11:30 AM",
    "FileNo": "26-041532",
    "PropAddress": "31948 County Road 6250",
    "PropCity": "Edgar Springs",
    "PropZip": "",
    "County": "Phelps",
    "OpeningBid": "$78,280",
    "vendor": "Auction.com",
    "status- DROP DOWN": "",
    "Foreclosure Status": ""
  },
  {
    "Trustee": "LOGS.COM",
    "Sale_date": "6/1/26",
    "Sale_time": "12:30 PM",
    "FileNo": "26-041584",
    "PropAddress": "203 Wild Winds Drive",
    "PropCity": "Ofallon",
    "PropZip": "",
    "County": "Saint Charles",
    "OpeningBid": "$127,300",
    "vendor": "Ascribe",
    "status- DROP DOWN": "",
    "Foreclosure Status": ""
  },
  {
    "Trustee": "LOGS.COM",
    "Sale_date": "6/3/26",
    "Sale_time": "10:00 AM",
    "FileNo": "26-041874",
    "PropAddress": "289 Greenshire Lane",
    "PropCity": "O Fallon",
    "PropZip": "",
    "County": "Saint Charles",
    "OpeningBid": "",
    "vendor": "Auction.com",
    "status- DROP DOWN": "",
    "Foreclosure Status": ""
  },
  {
    "Trustee": "LOGS.COM",
    "Sale_date": "6/1/26",
    "Sale_time": "11:30 AM",
    "FileNo": "25-041357",
    "PropAddress": "2570 Mullanphy Lane",
    "PropCity": "Florissant",
    "PropZip": "",
    "County": "Saint Louis",
    "OpeningBid": "",
    "vendor": "Auction.com",
    "status- DROP DOWN": "",
    "Foreclosure Status": ""
  },
  {
    "Trustee": "LOGS.COM",
    "Sale_date": "6/3/26",
    "Sale_time": "09:30 AM",
    "FileNo": "26-041665",
    "PropAddress": "6770 Aliceton Avenue",
    "PropCity": "Saint Louis",
    "PropZip": "",
    "County": "Saint Louis",
    "OpeningBid": "$151,700",
    "vendor": "Servicelink/Hudson Marshall",
    "status- DROP DOWN": "",
    "Foreclosure Status": ""
  },
  {
    "Trustee": "LOGS.COM",
    "Sale_date": "6/10/26",
    "Sale_time": "11:30 AM",
    "FileNo": "26-041856",
    "PropAddress": "2230 Riverwood Trails Drive",
    "PropCity": "Florissant",
    "PropZip": "",
    "County": "Saint Louis",
    "OpeningBid": "",
    "vendor": "Auction.com",
    "status- DROP DOWN": "",
    "Foreclosure Status": ""
  },
  {
    "Trustee": "LOGS.COM",
    "Sale_date": "6/3/26",
    "Sale_time": "11:00 AM",
    "FileNo": "26-041403",
    "PropAddress": "3231 Mount Pleasant St",
    "PropCity": "Saint Louis",
    "PropZip": "",
    "County": "Saint Louis City",
    "OpeningBid": "",
    "vendor": "Servicelink/Hudson Marshall",
    "status- DROP DOWN": "",
    "Foreclosure Status": ""
  },
  {
    "Trustee": "LOGS.COM",
    "Sale_date": "6/3/26",
    "Sale_time": "11:00 AM",
    "FileNo": "26-041657",
    "PropAddress": "6405 Hoffman Avenue",
    "PropCity": "Saint Louis",
    "PropZip": "",
    "County": "Saint Louis City",
    "OpeningBid": "$95,140",
    "vendor": "Ascribe",
    "status- DROP DOWN": "",
    "Foreclosure Status": ""
  },
  {
    "Trustee": "LOGS.COM",
    "Sale_date": "6/1/26",
    "Sale_time": "02:00 PM",
    "FileNo": "26-041476",
    "PropAddress": "302 E Allis",
    "PropCity": "Bernie",
    "PropZip": "",
    "County": "Stoddard",
    "OpeningBid": "$98,592.43",
    "vendor": "",
    "status- DROP DOWN": "",
    "Foreclosure Status": ""
  },
  {
    "Trustee": "LOGS.COM",
    "Sale_date": "5/29/26",
    "Sale_time": "01:30 PM",
    "FileNo": "26-041435",
    "PropAddress": "1709 Neihardt St",
    "PropCity": "Branson",
    "PropZip": "",
    "County": "Taney",
    "OpeningBid": "",
    "vendor": "",
    "status- DROP DOWN": "",
    "Foreclosure Status": ""
  }
]